django_crew/__init__.py
django_crew-0.1.0.dist-info/METADATA
django_crew-0.1.0.dist-info/WHEEL
django_crew-0.1.0.dist-info/RECORD
