Metadata-Version: 2.1
Name: django-crew
Version: 0.1.0
Summary: An implementation of Crew in Django. Secure AI Agents, especially delegation of actions and secrets, is the core guiding intention.
License: MIT
Author: Matthew Thompson
Author-email: thompsonson@gmail.com
Requires-Python: >=3.10,<4.0
Classifier: License :: OSI Approved :: MIT License
Classifier: Programming Language :: Python :: 3
Classifier: Programming Language :: Python :: 3.10
Classifier: Programming Language :: Python :: 3.11
Classifier: Programming Language :: Python :: 3.12
Requires-Dist: crew (>=0.9.2,<0.10.0)
